CHANGES.txt
COPYRIGHT.txt
LICENSE.txt
README.txt
TODO.txt
ez_setup.py
setup.cfg
setup.py
repoze/__init__.py
repoze.zope2.egg-info/PKG-INFO
repoze.zope2.egg-info/SOURCES.txt
repoze.zope2.egg-info/dependency_links.txt
repoze.zope2.egg-info/entry_points.txt
repoze.zope2.egg-info/namespace_packages.txt
repoze.zope2.egg-info/not-zip-safe
repoze.zope2.egg-info/requires.txt
repoze.zope2.egg-info/test_info.txt
repoze.zope2.egg-info/top_level.txt
repoze/zope2/__init__.py
repoze/zope2/db.py
repoze/zope2/instance.py
repoze/zope2/mapply.py
repoze/zope2/publishtraverse.py
repoze/zope2/request.py
repoze/zope2/server.py
repoze/zope2/z2bob.py
repoze/zope2/etc/apache2.conf
repoze/zope2/etc/zeo.conf
repoze/zope2/etc/zope-2.10+-site.zcml
repoze/zope2/etc/zope-2.9-site.zcml
repoze/zope2/etc/zope-nonzeoclient.conf
repoze/zope2/etc/zope-zeoclient.conf
repoze/zope2/etc/zope2.ini
repoze/zope2/etc/zope2.wsgi
repoze/zope2/scripts/__init__.py
repoze/zope2/scripts/adduser.py
repoze/zope2/scripts/debug.py
repoze/zope2/scripts/finder.py
repoze/zope2/scripts/installproduct.py
repoze/zope2/scripts/runscript.py
repoze/zope2/scripts/testrunner.py
repoze/zope2/scripts/wsgiloader.py
repoze/zope2/tests/__init__.py
repoze/zope2/tests/base.py
repoze/zope2/tests/test_db.py
repoze/zope2/tests/test_publishtraverse.py
repoze/zope2/tests/test_request.py
repoze/zope2/tests/test_scripts.py
repoze/zope2/tests/test_server.py
repoze/zope2/tests/test_z2bob.py